filedrop/__init__.py
filedrop/__main__.py
filedrop/server.py
filedrop-1.0.7.dist-info/LICENCE
filedrop-1.0.7.dist-info/METADATA
filedrop-1.0.7.dist-info/WHEEL
filedrop-1.0.7.dist-info/entry_points.txt
filedrop-1.0.7.dist-info/top_level.txt
filedrop-1.0.7.dist-info/RECORD
