Metadata-Version: 2.1
Name: filedrop
Version: 1.0.7
License: MIT
Classifier: Programming Language :: Python :: 3
Classifier: License :: OSI Approved :: MIT License
Classifier: Operating System :: OS Independent
Requires-Python: >=3.6
License-File: LICENCE
Requires-Dist: qrcode
Requires-Dist: pypng
